fckit
