Metadata-Version: 1.0
Name: fckit
Version: 12.3.0
Summary: Collection of prototyping functions and classes
Home-page: https://github.com/fclaerho/fckit
Author: florent claerhout
Author-email: code@fclaerhout.fr
License: MIT
Platform: UNKNOWN
